[
    {
        "course_code": "HW0288",
        "title": "ENGINEERING COMMUNICATION",
        "academic_units": "2.0 AU",
        "school_category": "Mechanical Engineering (IMS) Year 4",
        "exam": null,
        "indexes": [
            {
                "index_number": "10394",
                "lessons": [
                    {
                        "type": "TUT",
                        "group": "TCEA",
                        "day": "MON",
                        "time": "0830-1020",
                        "venue": "TR+64",
                        "remark": "Teaching Wk2-13"
                    }
                ]
            },
            {
                "index_number": "10395",
                "lessons": [
                    {
                        "type": "TUT",
                        "group": "TCEB",
                        "day": "WED",
                        "time": "1230-1420",
                        "venue": "TR+23",
                        "remark": "Teaching Wk2-13"
                    }
                ]
            },
            {
                "index_number": "10396",
                "lessons": [
                    {
                        "type": "TUT",
                        "group": "TCEC",
                        "day": "MON",
                        "time": "1030-1220",
                        "venue": "TR+33",
                        "remark": "Teaching Wk2-13"
                    }
                ]
            },
            {
                "index_number": "10397",
                "lessons": [
                    {
                        "type": "TUT",
                        "group": "TCED",
                        "day": "FRI",
                        "time": "1130-1320",
                        "venue": "CSKL8",
                        "remark": "Teaching Wk2-13"
                    }
                ]
            },
            {
                "index_number": "10398",
                "lessons": [
                    {
                        "type": "TUT",
                        "group": "TCEE",
                        "day": "WED",
                        "time": "1230-1420",
                        "venue": "TR+32",
                        "remark": "Teaching Wk2-13"
                    }
                ]
            },
            {
                "index_number": "10399",
                "lessons": [
                    {
                        "type": "TUT",
                        "group": "TCE1",
                        "day": "THU",
                        "time": "1630-1820",
                        "venue": "TR+95",
                        "remark": "Teaching Wk2-13"
                    }
                ]
            },
            {
                "index_number": "10400",
                "lessons": [
                    {
                        "type": "TUT",
                        "group": "TCSA",
                        "day": "TUE",
                        "time": "1030-1220",
                        "venue": "TR+37",
                        "remark": "Teaching Wk2-13"
                    }
                ]
            },
            {
                "index_number": "10401",
                "lessons": [
                    {
                        "type": "TUT",
                        "group": "TCSB",
                        "day": "MON",
                        "time": "1430-1620",
                        "venue": "TR+31",
                        "remark": "Teaching Wk2-13"
                    }
                ]
            },
            {
                "index_number": "10402",
                "lessons": [
                    {
                        "type": "TUT",
                        "group": "TCSC",
                        "day": "MON",
                        "time": "1430-1620",
                        "venue": "TR+34",
                        "remark": "Teaching Wk2-13"
                    }
                ]
            },
            {
                "index_number": "10403",
                "lessons": [
                    {
                        "type": "TUT",
                        "group": "TCSD",
                        "day": "FRI",
                        "time": "1230-1420",
                        "venue": "TR+37",
                        "remark": "Teaching Wk2-13"
                    }
                ]
            },
            {
                "index_number": "10404",
                "lessons": [
                    {
                        "type": "TUT",
                        "group": "TCSE",
                        "day": "FRI",
                        "time": "1230-1420",
                        "venue": "LHN-TR+18",
                        "remark": "Teaching Wk2-13"
                    }
                ]
            },
            {
                "index_number": "10405",
                "lessons": [
                    {
                        "type": "TUT",
                        "group": "TCSF",
                        "day": "WED",
                        "time": "1230-1420",
                        "venue": "TR+37",
                        "remark": "Teaching Wk2-13"
                    }
                ]
            },
            {
                "index_number": "10406",
                "lessons": [
                    {
                        "type": "TUT",
                        "group": "TCSG",
                        "day": "THU",
                        "time": "1230-1420",
                        "venue": "TR+77",
                        "remark": "Teaching Wk2-13"
                    }
                ]
            },
            {
                "index_number": "10407",
                "lessons": [
                    {
                        "type": "TUT",
                        "group": "TCSH",
                        "day": "THU",
                        "time": "1230-1420",
                        "venue": "TR+33",
                        "remark": "Teaching Wk2-13"
                    }
                ]
            },
            {
                "index_number": "10408",
                "lessons": [
                    {
                        "type": "TUT",
                        "group": "TCSI",
                        "day": "THU",
                        "time": "0830-1020",
                        "venue": "TR+33",
                        "remark": "Teaching Wk2-13"
                    }
                ]
            },
            {
                "index_number": "10410",
                "lessons": [
                    {
                        "type": "TUT",
                        "group": "TCS1",
                        "day": "TUE",
                        "time": "1030-1220",
                        "venue": "CSKL9",
                        "remark": "Teaching Wk2-13"
                    }
                ]
            },
            {
                "index_number": "10411",
                "lessons": [
                    {
                        "type": "TUT",
                        "group": "TCMA",
                        "day": "TUE",
                        "time": "1330-1520",
                        "venue": "TR+33",
                        "remark": "Teaching Wk2-13"
                    }
                ]
            },
            {
                "index_number": "10412",
                "lessons": [
                    {
                        "type": "TUT",
                        "group": "TCMC",
                        "day": "THU",
                        "time": "1630-1820",
                        "venue": "TR+33",
                        "remark": "Teaching Wk2-13"
                    }
                ]
            },
            {
                "index_number": "10413",
                "lessons": [
                    {
                        "type": "TUT",
                        "group": "TCMD",
                        "day": "THU",
                        "time": "1030-1220",
                        "venue": "TR+33",
                        "remark": "Teaching Wk2-13"
                    }
                ]
            },
            {
                "index_number": "23030",
                "lessons": [
                    {
                        "type": "TUT",
                        "group": "MA4",
                        "day": "MON",
                        "time": "1330-1520",
                        "venue": "LHN-TR+20",
                        "remark": "Teaching Wk2-13"
                    }
                ]
            },
            {
                "index_number": "23031",
                "lessons": [
                    {
                        "type": "TUT",
                        "group": "MA5",
                        "day": "TUE",
                        "time": "0930-1120",
                        "venue": "LHN-TR+17",
                        "remark": "Teaching Wk2-13"
                    }
                ]
            },
            {
                "index_number": "23032",
                "lessons": [
                    {
                        "type": "TUT",
                        "group": "MA6",
                        "day": "TUE",
                        "time": "1130-1320",
                        "venue": "TR+21",
                        "remark": "Teaching Wk2-13"
                    }
                ]
            },
            {
                "index_number": "23037",
                "lessons": [
                    {
                        "type": "TUT",
                        "group": "MA11",
                        "day": "WED",
                        "time": "1130-1320",
                        "venue": "LHN-TR+21",
                        "remark": "Teaching Wk2-13"
                    }
                ]
            },
            {
                "index_number": "23038",
                "lessons": [
                    {
                        "type": "TUT",
                        "group": "MA12",
                        "day": "THU",
                        "time": "0930-1120",
                        "venue": "TR+32",
                        "remark": "Teaching Wk2-13"
                    }
                ]
            },
            {
                "index_number": "23039",
                "lessons": [
                    {
                        "type": "TUT",
                        "group": "MA13",
                        "day": "THU",
                        "time": "1130-1320",
                        "venue": "TR+32",
                        "remark": "Teaching Wk2-13"
                    }
                ]
            },
            {
                "index_number": "23040",
                "lessons": [
                    {
                        "type": "TUT",
                        "group": "MA14",
                        "day": "THU",
                        "time": "1130-1320",
                        "venue": "LHN-TR+17",
                        "remark": "Teaching Wk2-13"
                    }
                ]
            },
            {
                "index_number": "23042",
                "lessons": [
                    {
                        "type": "TUT",
                        "group": "MA16",
                        "day": "FRI",
                        "time": "0930-1120",
                        "venue": "LHN-TR+17",
                        "remark": "Teaching Wk2-13"
                    }
                ]
            }
        ]
    },
    {
        "course_code": "MA0218",
        "title": "INTRODUCTION TO DATA SCIENCE & ARTIFICIAL INTELLIGENCE*",
        "academic_units": "3.0 AU",
        "school_category": "Mechanical Engineering (IMS) Year 4",
        "exam": null,
        "indexes": [
            {
                "index_number": "23043",
                "lessons": [
                    {
                        "type": "LEC/STUDIO",
                        "group": "LE",
                        "day": "FRI",
                        "time": "0930-1020",
                        "venue": "LT14",
                        "remark": ""
                    },
                    {
                        "type": "TUT",
                        "group": "MA1",
                        "day": "MON",
                        "time": "1330-1520",
                        "venue": "CAE 2 LAB",
                        "remark": "Teaching Wk2-13"
                    }
                ]
            },
            {
                "index_number": "23044",
                "lessons": [
                    {
                        "type": "LEC/STUDIO",
                        "group": "LE",
                        "day": "FRI",
                        "time": "0930-1020",
                        "venue": "LT14",
                        "remark": ""
                    },
                    {
                        "type": "TUT",
                        "group": "MA2",
                        "day": "MON",
                        "time": "1330-1520",
                        "venue": "CAE 2 LAB",
                        "remark": "Teaching Wk2-13"
                    }
                ]
            },
            {
                "index_number": "23045",
                "lessons": [
                    {
                        "type": "LEC/STUDIO",
                        "group": "LE",
                        "day": "FRI",
                        "time": "0930-1020",
                        "venue": "LT14",
                        "remark": ""
                    },
                    {
                        "type": "TUT",
                        "group": "MA3",
                        "day": "MON",
                        "time": "1530-1720",
                        "venue": "CAE 2 LAB",
                        "remark": "Teaching Wk2-13"
                    }
                ]
            },
            {
                "index_number": "23046",
                "lessons": [
                    {
                        "type": "LEC/STUDIO",
                        "group": "LE",
                        "day": "FRI",
                        "time": "0930-1020",
                        "venue": "LT14",
                        "remark": ""
                    },
                    {
                        "type": "TUT",
                        "group": "MA4",
                        "day": "MON",
                        "time": "1530-1720",
                        "venue": "CAE 2 LAB",
                        "remark": "Teaching Wk2-13"
                    }
                ]
            },
            {
                "index_number": "23047",
                "lessons": [
                    {
                        "type": "LEC/STUDIO",
                        "group": "LE",
                        "day": "FRI",
                        "time": "0930-1020",
                        "venue": "LT14",
                        "remark": ""
                    },
                    {
                        "type": "TUT",
                        "group": "MA5",
                        "day": "TUE",
                        "time": "0830-1020",
                        "venue": "CAE 2 LAB",
                        "remark": "Teaching Wk2-13"
                    }
                ]
            },
            {
                "index_number": "23048",
                "lessons": [
                    {
                        "type": "LEC/STUDIO",
                        "group": "LE",
                        "day": "FRI",
                        "time": "0930-1020",
                        "venue": "LT14",
                        "remark": ""
                    },
                    {
                        "type": "TUT",
                        "group": "MA6",
                        "day": "TUE",
                        "time": "0830-1020",
                        "venue": "CAE 2 LAB",
                        "remark": "Teaching Wk2-13"
                    }
                ]
            },
            {
                "index_number": "23049",
                "lessons": [
                    {
                        "type": "LEC/STUDIO",
                        "group": "LE",
                        "day": "FRI",
                        "time": "0930-1020",
                        "venue": "LT14",
                        "remark": ""
                    },
                    {
                        "type": "TUT",
                        "group": "MA7",
                        "day": "WED",
                        "time": "1330-1520",
                        "venue": "CAE 2 LAB",
                        "remark": "Teaching Wk2-13"
                    }
                ]
            },
            {
                "index_number": "23050",
                "lessons": [
                    {
                        "type": "LEC/STUDIO",
                        "group": "LE",
                        "day": "FRI",
                        "time": "0930-1020",
                        "venue": "LT14",
                        "remark": ""
                    },
                    {
                        "type": "TUT",
                        "group": "MA8",
                        "day": "WED",
                        "time": "1530-1720",
                        "venue": "CAE 2 LAB",
                        "remark": "Teaching Wk2-13"
                    }
                ]
            },
            {
                "index_number": "23051",
                "lessons": [
                    {
                        "type": "LEC/STUDIO",
                        "group": "LE",
                        "day": "FRI",
                        "time": "0930-1020",
                        "venue": "LT14",
                        "remark": ""
                    },
                    {
                        "type": "TUT",
                        "group": "MA9",
                        "day": "THU",
                        "time": "0830-1020",
                        "venue": "CAE 2 LAB",
                        "remark": "Teaching Wk2-13"
                    }
                ]
            },
            {
                "index_number": "23052",
                "lessons": [
                    {
                        "type": "LEC/STUDIO",
                        "group": "LE",
                        "day": "FRI",
                        "time": "0930-1020",
                        "venue": "LT14",
                        "remark": ""
                    },
                    {
                        "type": "TUT",
                        "group": "MA10",
                        "day": "THU",
                        "time": "0830-1020",
                        "venue": "CAE 2 LAB",
                        "remark": "Teaching Wk2-13"
                    }
                ]
            }
        ]
    },
    {
        "course_code": "MA4001",
        "title": "ENGINEERING DESIGN",
        "academic_units": "4.0 AU",
        "school_category": "Mechanical Engineering (IMS) Year 4",
        "exam": {
            "date": "1 December 2026",
            "day": "Tuesday",
            "time": "9.00 am",
            "duration": "2 hr 30 min"
        },
        "indexes": [
            {
                "index_number": "23402",
                "lessons": [
                    {
                        "type": "LEC/STUDIO",
                        "group": "LE",
                        "day": "MON",
                        "time": "1130-1220",
                        "venue": "LT1A",
                        "remark": ""
                    },
                    {
                        "type": "TUT",
                        "group": "MA1",
                        "day": "MON",
                        "time": "1330-1620",
                        "venue": "LHN-TR+18",
                        "remark": "Teaching Wk2-13"
                    }
                ]
            },
            {
                "index_number": "23403",
                "lessons": [
                    {
                        "type": "LEC/STUDIO",
                        "group": "LE",
                        "day": "MON",
                        "time": "1130-1220",
                        "venue": "LT1A",
                        "remark": ""
                    },
                    {
                        "type": "TUT",
                        "group": "MA2",
                        "day": "MON",
                        "time": "1330-1620",
                        "venue": "LHN-TR+07",
                        "remark": "Teaching Wk2-13"
                    }
                ]
            },
            {
                "index_number": "23404",
                "lessons": [
                    {
                        "type": "LEC/STUDIO",
                        "group": "LE",
                        "day": "MON",
                        "time": "1130-1220",
                        "venue": "LT1A",
                        "remark": ""
                    },
                    {
                        "type": "TUT",
                        "group": "MA3",
                        "day": "TUE",
                        "time": "1330-1620",
                        "venue": "LHN-TR+08",
                        "remark": "Teaching Wk2-13"
                    }
                ]
            },
            {
                "index_number": "23405",
                "lessons": [
                    {
                        "type": "LEC/STUDIO",
                        "group": "LE",
                        "day": "MON",
                        "time": "1130-1220",
                        "venue": "LT1A",
                        "remark": ""
                    },
                    {
                        "type": "TUT",
                        "group": "MA4",
                        "day": "TUE",
                        "time": "1330-1620",
                        "venue": "LHN-TR+07",
                        "remark": "Teaching Wk2-13"
                    }
                ]
            },
            {
                "index_number": "23406",
                "lessons": [
                    {
                        "type": "LEC/STUDIO",
                        "group": "LE",
                        "day": "MON",
                        "time": "1130-1220",
                        "venue": "LT1A",
                        "remark": ""
                    },
                    {
                        "type": "TUT",
                        "group": "MA5",
                        "day": "WED",
                        "time": "1330-1620",
                        "venue": "LHN-TR+08",
                        "remark": "Teaching Wk2-13"
                    }
                ]
            },
            {
                "index_number": "23407",
                "lessons": [
                    {
                        "type": "LEC/STUDIO",
                        "group": "LE",
                        "day": "MON",
                        "time": "1130-1220",
                        "venue": "LT1A",
                        "remark": ""
                    },
                    {
                        "type": "TUT",
                        "group": "MA6",
                        "day": "WED",
                        "time": "1330-1620",
                        "venue": "LHN-TR+18",
                        "remark": "Teaching Wk2-13"
                    }
                ]
            },
            {
                "index_number": "23408",
                "lessons": [
                    {
                        "type": "LEC/STUDIO",
                        "group": "LE",
                        "day": "MON",
                        "time": "1130-1220",
                        "venue": "LT1A",
                        "remark": ""
                    },
                    {
                        "type": "TUT",
                        "group": "MA7",
                        "day": "THU",
                        "time": "1330-1620",
                        "venue": "LHN-TR+07",
                        "remark": "Teaching Wk2-13"
                    }
                ]
            },
            {
                "index_number": "23409",
                "lessons": [
                    {
                        "type": "LEC/STUDIO",
                        "group": "LE",
                        "day": "MON",
                        "time": "1130-1220",
                        "venue": "LT1A",
                        "remark": ""
                    },
                    {
                        "type": "TUT",
                        "group": "MA8",
                        "day": "THU",
                        "time": "1330-1620",
                        "venue": "LHN-TR+33",
                        "remark": "Teaching Wk2-13"
                    }
                ]
            }
        ]
    },
    {
        "course_code": "MA4804",
        "title": "OPTIMIZATION THEORY & APPLICATIONS~",
        "academic_units": "3.0 AU",
        "school_category": "Mechanical Engineering (IMS) Year 4",
        "exam": {
            "date": "25 November 2026",
            "day": "Wednesday",
            "time": "9.00 am",
            "duration": "2 hr"
        },
        "indexes": [
            {
                "index_number": "23421",
                "lessons": [
                    {
                        "type": "LEC/STUDIO",
                        "group": "LE",
                        "day": "THU",
                        "time": "1330-1520",
                        "venue": "LT4",
                        "remark": ""
                    }
                ]
            }
        ]
    },
    {
        "course_code": "MA4811",
        "title": "PSYCHROMETRY & AIR CONDITIONING~",
        "academic_units": "3.0 AU",
        "school_category": "Mechanical Engineering (IMS) Year 4",
        "exam": {
            "date": "3 December 2026",
            "day": "Thursday",
            "time": "1.00 pm",
            "duration": "2 hr 30 min"
        },
        "indexes": [
            {
                "index_number": "23422",
                "lessons": [
                    {
                        "type": "LEC/STUDIO",
                        "group": "LE",
                        "day": "MON",
                        "time": "1530-1620",
                        "venue": "LHN-LT",
                        "remark": ""
                    },
                    {
                        "type": "LEC/STUDIO",
                        "group": "LE",
                        "day": "WED",
                        "time": "1630-1820",
                        "venue": "LHN-LT",
                        "remark": ""
                    }
                ]
            }
        ]
    },
    {
        "course_code": "MA4814",
        "title": "COMPUTATIONAL FLUID DYNAMICS~",
        "academic_units": "3.0 AU",
        "school_category": "Mechanical Engineering (IMS) Year 4",
        "exam": null,
        "indexes": [
            {
                "index_number": "23423",
                "lessons": [
                    {
                        "type": "LEC/STUDIO",
                        "group": "LE",
                        "day": "TUE",
                        "time": "0830-1020",
                        "venue": "LT13",
                        "remark": ""
                    },
                    {
                        "type": "TUT",
                        "group": "MA1",
                        "day": "THU",
                        "time": "1330-1420",
                        "venue": "N3-B3B-05",
                        "remark": "Teaching Wk2-7"
                    },
                    {
                        "type": "TUT",
                        "group": "MA1",
                        "day": "THU",
                        "time": "1330-1620",
                        "venue": "N3-B3B-05",
                        "remark": "Teaching Wk8-13"
                    }
                ]
            }
        ]
    },
    {
        "course_code": "MA4822",
        "title": "MEASUREMENTS & SENSING SYSTEMS~",
        "academic_units": "3.0 AU",
        "school_category": "Mechanical Engineering (IMS) Year 4",
        "exam": null,
        "indexes": [
            {
                "index_number": "23424",
                "lessons": [
                    {
                        "type": "LEC/STUDIO",
                        "group": "LE",
                        "day": "FRI",
                        "time": "0830-1020",
                        "venue": "LT13",
                        "remark": ""
                    },
                    {
                        "type": "LEC/STUDIO",
                        "group": "LE",
                        "day": "MON",
                        "time": "1630-1720",
                        "venue": "LT11",
                        "remark": ""
                    }
                ]
            }
        ]
    },
    {
        "course_code": "MA4825",
        "title": "ROBOTICS~",
        "academic_units": "3.0 AU",
        "school_category": "Mechanical Engineering (IMS) Year 4",
        "exam": {
            "date": "3 December 2026",
            "day": "Thursday",
            "time": "9.00 am",
            "duration": "2 hr"
        },
        "indexes": [
            {
                "index_number": "23425",
                "lessons": [
                    {
                        "type": "LEC/STUDIO",
                        "group": "LE",
                        "day": "MON",
                        "time": "1330-1520",
                        "venue": "LT13",
                        "remark": ""
                    },
                    {
                        "type": "LEC/STUDIO",
                        "group": "LE",
                        "day": "WED",
                        "time": "1730-1820",
                        "venue": "LT13",
                        "remark": ""
                    }
                ]
            }
        ]
    },
    {
        "course_code": "MA4832",
        "title": "MICROPROCESSOR SYSTEMS~",
        "academic_units": "3.0 AU",
        "school_category": "Mechanical Engineering (IMS) Year 4",
        "exam": {
            "date": "1 December 2026",
            "day": "Tuesday",
            "time": "5.00 pm",
            "duration": "2 hr 30 min"
        },
        "indexes": [
            {
                "index_number": "23426",
                "lessons": [
                    {
                        "type": "LEC/STUDIO",
                        "group": "LE",
                        "day": "MON",
                        "time": "0930-1120",
                        "venue": "LT6",
                        "remark": ""
                    },
                    {
                        "type": "TUT",
                        "group": "MA1",
                        "day": "THU",
                        "time": "0930-1020",
                        "venue": "N3.2-B1-03",
                        "remark": ""
                    }
                ]
            },
            {
                "index_number": "23427",
                "lessons": [
                    {
                        "type": "LEC/STUDIO",
                        "group": "LE",
                        "day": "MON",
                        "time": "0930-1120",
                        "venue": "LT6",
                        "remark": ""
                    },
                    {
                        "type": "TUT",
                        "group": "MA2",
                        "day": "THU",
                        "time": "1030-1120",
                        "venue": "N3.2-B1-03",
                        "remark": ""
                    }
                ]
            }
        ]
    },
    {
        "course_code": "MA4849",
        "title": "OPERATIONS RESEARCH~",
        "academic_units": "3.0 AU",
        "school_category": "Mechanical Engineering (IMS) Year 4",
        "exam": {
            "date": "30 November 2026",
            "day": "Monday",
            "time": "1.00 pm",
            "duration": "2 hr 30 min"
        },
        "indexes": [
            {
                "index_number": "23429",
                "lessons": [
                    {
                        "type": "LEC/STUDIO",
                        "group": "LE",
                        "day": "WED",
                        "time": "1230-1320",
                        "venue": "LHN-LT",
                        "remark": ""
                    },
                    {
                        "type": "LEC/STUDIO",
                        "group": "LE",
                        "day": "TUE",
                        "time": "1430-1620",
                        "venue": "LHN-LT",
                        "remark": ""
                    }
                ]
            }
        ]
    },
    {
        "course_code": "MA4856",
        "title": "NAVAL ARCHITECTURE & MARINE ENGINEERING~",
        "academic_units": "3.0 AU",
        "school_category": "Mechanical Engineering (IMS) Year 4",
        "exam": {
            "date": "24 November 2026",
            "day": "Tuesday",
            "time": "1.00 pm",
            "duration": "2 hr 30 min"
        },
        "indexes": [
            {
                "index_number": "23430",
                "lessons": [
                    {
                        "type": "LEC/STUDIO",
                        "group": "LE",
                        "day": "MON",
                        "time": "1030-1120",
                        "venue": "LT16",
                        "remark": ""
                    },
                    {
                        "type": "LEC/STUDIO",
                        "group": "LE",
                        "day": "TUE",
                        "time": "1530-1720",
                        "venue": "LT15",
                        "remark": ""
                    }
                ]
            }
        ]
    },
    {
        "course_code": "MA4880",
        "title": "AIRPORT OPERATIONS & SYSTEMS~",
        "academic_units": "3.0 AU",
        "school_category": "Mechanical Engineering (IMS) Year 4",
        "exam": {
            "date": "3 December 2026",
            "day": "Thursday",
            "time": "1.00 pm",
            "duration": "2 hr"
        },
        "indexes": [
            {
                "index_number": "23482",
                "lessons": [
                    {
                        "type": "LEC/STUDIO",
                        "group": "LE",
                        "day": "TUE",
                        "time": "1030-1220",
                        "venue": "LT18",
                        "remark": ""
                    },
                    {
                        "type": "TUT",
                        "group": "MA1",
                        "day": "TUE",
                        "time": "1330-1420",
                        "venue": "LHN-TR+40",
                        "remark": "Teaching Wk2-13"
                    }
                ]
            },
            {
                "index_number": "23483",
                "lessons": [
                    {
                        "type": "LEC/STUDIO",
                        "group": "LE",
                        "day": "TUE",
                        "time": "1030-1220",
                        "venue": "LT18",
                        "remark": ""
                    },
                    {
                        "type": "TUT",
                        "group": "MA2",
                        "day": "TUE",
                        "time": "1430-1520",
                        "venue": "LHN-TR+40",
                        "remark": "Teaching Wk2-13"
                    }
                ]
            },
            {
                "index_number": "23484",
                "lessons": [
                    {
                        "type": "LEC/STUDIO",
                        "group": "LE",
                        "day": "TUE",
                        "time": "1030-1220",
                        "venue": "LT18",
                        "remark": ""
                    },
                    {
                        "type": "TUT",
                        "group": "MA3",
                        "day": "TUE",
                        "time": "1530-1620",
                        "venue": "LHN-TR+40",
                        "remark": "Teaching Wk2-13"
                    }
                ]
            },
            {
                "index_number": "23485",
                "lessons": [
                    {
                        "type": "LEC/STUDIO",
                        "group": "LE",
                        "day": "TUE",
                        "time": "1030-1220",
                        "venue": "LT18",
                        "remark": ""
                    },
                    {
                        "type": "TUT",
                        "group": "MA4",
                        "day": "TUE",
                        "time": "1630-1720",
                        "venue": "LHN-TR+40",
                        "remark": "Teaching Wk2-13"
                    }
                ]
            }
        ]
    },
    {
        "course_code": "MA4881",
        "title": "AIR TRAFFIC MANAGEMENT~",
        "academic_units": "3.0 AU",
        "school_category": "Mechanical Engineering (IMS) Year 4",
        "exam": {
            "date": "27 November 2026",
            "day": "Friday",
            "time": "2.30 pm",
            "duration": "2 hr"
        },
        "indexes": [
            {
                "index_number": "23487",
                "lessons": [
                    {
                        "type": "LEC/STUDIO",
                        "group": "LE",
                        "day": "MON",
                        "time": "0830-1020",
                        "venue": "LT13",
                        "remark": ""
                    },
                    {
                        "type": "TUT",
                        "group": "MA1",
                        "day": "MON",
                        "time": "1330-1420",
                        "venue": "LHN-TR+31",
                        "remark": "Teaching Wk2-13"
                    }
                ]
            },
            {
                "index_number": "23488",
                "lessons": [
                    {
                        "type": "LEC/STUDIO",
                        "group": "LE",
                        "day": "MON",
                        "time": "0830-1020",
                        "venue": "LT13",
                        "remark": ""
                    },
                    {
                        "type": "TUT",
                        "group": "MA2",
                        "day": "MON",
                        "time": "1430-1520",
                        "venue": "LHN-TR+31",
                        "remark": "Teaching Wk2-13"
                    }
                ]
            },
            {
                "index_number": "23489",
                "lessons": [
                    {
                        "type": "LEC/STUDIO",
                        "group": "LE",
                        "day": "MON",
                        "time": "0830-1020",
                        "venue": "LT13",
                        "remark": ""
                    },
                    {
                        "type": "TUT",
                        "group": "MA3",
                        "day": "MON",
                        "time": "1530-1620",
                        "venue": "LHN-TR+31",
                        "remark": "Teaching Wk2-13"
                    }
                ]
            },
            {
                "index_number": "23490",
                "lessons": [
                    {
                        "type": "LEC/STUDIO",
                        "group": "LE",
                        "day": "MON",
                        "time": "0830-1020",
                        "venue": "LT13",
                        "remark": ""
                    },
                    {
                        "type": "TUT",
                        "group": "MA4",
                        "day": "MON",
                        "time": "1630-1720",
                        "venue": "LHN-TR+31",
                        "remark": "Teaching Wk2-13"
                    }
                ]
            }
        ]
    },
    {
        "course_code": "MA4884",
        "title": "SYSTEMS THINKING & SYSTEMS ENGINEERING~",
        "academic_units": "3.0 AU",
        "school_category": "Mechanical Engineering (IMS) Year 4",
        "exam": {
            "date": "23 November 2026",
            "day": "Monday",
            "time": "5.00 pm",
            "duration": "2 hr 30 min"
        },
        "indexes": [
            {
                "index_number": "23436",
                "lessons": [
                    {
                        "type": "LEC/STUDIO",
                        "group": "LE",
                        "day": "WED",
                        "time": "1330-1620",
                        "venue": "LT13",
                        "remark": ""
                    }
                ]
            }
        ]
    }
]