[
    {
        "course_code": "HH1001",
        "title": "WHAT IS HISTORY?*~",
        "academic_units": "3.0 AU",
        "school_category": "Minor in History",
        "exam": {
            "date": "2 December 2026",
            "day": "Wednesday",
            "time": "5.00 pm",
            "duration": "2 hr 30 min"
        },
        "indexes": [
            {
                "index_number": "17601",
                "lessons": [
                    {
                        "type": "LEC/STUDIO",
                        "group": "LEC1",
                        "day": "TUE",
                        "time": "1230-1420",
                        "venue": "HSSAUDIT",
                        "remark": ""
                    },
                    {
                        "type": "TUT",
                        "group": "T1",
                        "day": "TUE",
                        "time": "1430-1520",
                        "venue": "HSS-TR+2",
                        "remark": "Teaching Wk2-13"
                    }
                ]
            },
            {
                "index_number": "17602",
                "lessons": [
                    {
                        "type": "LEC/STUDIO",
                        "group": "LEC1",
                        "day": "TUE",
                        "time": "1230-1420",
                        "venue": "HSSAUDIT",
                        "remark": ""
                    },
                    {
                        "type": "TUT",
                        "group": "T2",
                        "day": "TUE",
                        "time": "1530-1620",
                        "venue": "TR+95",
                        "remark": "Teaching Wk2-13"
                    }
                ]
            },
            {
                "index_number": "17603",
                "lessons": [
                    {
                        "type": "LEC/STUDIO",
                        "group": "LEC1",
                        "day": "TUE",
                        "time": "1230-1420",
                        "venue": "HSSAUDIT",
                        "remark": ""
                    },
                    {
                        "type": "TUT",
                        "group": "T3",
                        "day": "TUE",
                        "time": "1630-1720",
                        "venue": "TR+95",
                        "remark": "Teaching Wk2-13"
                    }
                ]
            },
            {
                "index_number": "17604",
                "lessons": [
                    {
                        "type": "LEC/STUDIO",
                        "group": "LEC1",
                        "day": "TUE",
                        "time": "1230-1420",
                        "venue": "HSSAUDIT",
                        "remark": ""
                    },
                    {
                        "type": "TUT",
                        "group": "T4",
                        "day": "TUE",
                        "time": "1730-1820",
                        "venue": "TR+95",
                        "remark": "Teaching Wk2-13"
                    }
                ]
            }
        ]
    },
    {
        "course_code": "HH1002",
        "title": "ASIA-PACIFIC IN GLOBAL HISTORY: PRE-1800*~",
        "academic_units": "3.0 AU",
        "school_category": "Minor in History",
        "exam": null,
        "indexes": [
            {
                "index_number": "17605",
                "lessons": [
                    {
                        "type": "LEC/STUDIO",
                        "group": "LEC1",
                        "day": "FRI",
                        "time": "1230-1420",
                        "venue": "LT29",
                        "remark": ""
                    },
                    {
                        "type": "TUT",
                        "group": "T1",
                        "day": "FRI",
                        "time": "1430-1520",
                        "venue": "TR+92",
                        "remark": "Teaching Wk2-13"
                    }
                ]
            },
            {
                "index_number": "17606",
                "lessons": [
                    {
                        "type": "LEC/STUDIO",
                        "group": "LEC1",
                        "day": "FRI",
                        "time": "1230-1420",
                        "venue": "LT29",
                        "remark": ""
                    },
                    {
                        "type": "TUT",
                        "group": "T2",
                        "day": "FRI",
                        "time": "1530-1620",
                        "venue": "LHS-TR+29",
                        "remark": "Teaching Wk2-13"
                    }
                ]
            },
            {
                "index_number": "17607",
                "lessons": [
                    {
                        "type": "LEC/STUDIO",
                        "group": "LEC1",
                        "day": "FRI",
                        "time": "1230-1420",
                        "venue": "LT29",
                        "remark": ""
                    },
                    {
                        "type": "TUT",
                        "group": "T3",
                        "day": "FRI",
                        "time": "1630-1720",
                        "venue": "LHS-TR+29",
                        "remark": "Teaching Wk2-13"
                    }
                ]
            },
            {
                "index_number": "17608",
                "lessons": [
                    {
                        "type": "LEC/STUDIO",
                        "group": "LEC1",
                        "day": "FRI",
                        "time": "1230-1420",
                        "venue": "LT29",
                        "remark": ""
                    },
                    {
                        "type": "TUT",
                        "group": "T4",
                        "day": "FRI",
                        "time": "1730-1820",
                        "venue": "LHS-TR+29",
                        "remark": "Teaching Wk2-13"
                    }
                ]
            }
        ]
    },
    {
        "course_code": "HH1004",
        "title": "SCIENCE & TECHNOLOGY IN HISTORICAL PERSPECTIVE*~",
        "academic_units": "3.0 AU",
        "school_category": "Minor in History",
        "exam": {
            "date": "30 November 2026",
            "day": "Monday",
            "time": "1.00 pm",
            "duration": "2 hr 30 min"
        },
        "indexes": [
            {
                "index_number": "17632",
                "lessons": [
                    {
                        "type": "SEM",
                        "group": "SEM1",
                        "day": "WED",
                        "time": "0930-1220",
                        "venue": "LHS-TR+33",
                        "remark": ""
                    }
                ]
            }
        ]
    },
    {
        "course_code": "HH2009",
        "title": "CHINA IN REVOLUTION & REFORM*~",
        "academic_units": "3.0 AU",
        "school_category": "Minor in History",
        "exam": null,
        "indexes": [
            {
                "index_number": "17609",
                "lessons": [
                    {
                        "type": "SEM",
                        "group": "SEM1",
                        "day": "WED",
                        "time": "1330-1620",
                        "venue": "LHS-TR+36",
                        "remark": ""
                    }
                ]
            }
        ]
    },
    {
        "course_code": "HH2033",
        "title": "TOTAL WAR IN ASIA & THE PACIFIC, 1931-1951~",
        "academic_units": "3.0 AU",
        "school_category": "Minor in History",
        "exam": null,
        "indexes": [
            {
                "index_number": "17613",
                "lessons": [
                    {
                        "type": "LEC/STUDIO",
                        "group": "LEC1",
                        "day": "MON",
                        "time": "1230-1420",
                        "venue": "LT29",
                        "remark": ""
                    },
                    {
                        "type": "TUT",
                        "group": "T1",
                        "day": "MON",
                        "time": "1430-1520",
                        "venue": "TR+92",
                        "remark": "Teaching Wk2-13"
                    }
                ]
            },
            {
                "index_number": "17614",
                "lessons": [
                    {
                        "type": "LEC/STUDIO",
                        "group": "LEC1",
                        "day": "MON",
                        "time": "1230-1420",
                        "venue": "LT29",
                        "remark": ""
                    },
                    {
                        "type": "TUT",
                        "group": "T2",
                        "day": "MON",
                        "time": "1530-1620",
                        "venue": "LHS-TR+25",
                        "remark": "Teaching Wk2-13"
                    }
                ]
            },
            {
                "index_number": "17615",
                "lessons": [
                    {
                        "type": "LEC/STUDIO",
                        "group": "LEC1",
                        "day": "MON",
                        "time": "1230-1420",
                        "venue": "LT29",
                        "remark": ""
                    },
                    {
                        "type": "TUT",
                        "group": "T3",
                        "day": "MON",
                        "time": "1630-1720",
                        "venue": "LHS-TR+25",
                        "remark": "Teaching Wk2-13"
                    }
                ]
            },
            {
                "index_number": "17616",
                "lessons": [
                    {
                        "type": "LEC/STUDIO",
                        "group": "LEC1",
                        "day": "MON",
                        "time": "1230-1420",
                        "venue": "LT29",
                        "remark": ""
                    },
                    {
                        "type": "TUT",
                        "group": "T4",
                        "day": "MON",
                        "time": "1730-1820",
                        "venue": "LHS-TR+25",
                        "remark": "Teaching Wk2-13"
                    }
                ]
            }
        ]
    },
    {
        "course_code": "HH2046",
        "title": "URBAN HISTORY*~",
        "academic_units": "3.0 AU",
        "school_category": "Minor in History",
        "exam": null,
        "indexes": [
            {
                "index_number": "17617",
                "lessons": [
                    {
                        "type": "SEM",
                        "group": "SEM1",
                        "day": "FRI",
                        "time": "1030-1320",
                        "venue": "LHS-TR+32",
                        "remark": ""
                    }
                ]
            }
        ]
    },
    {
        "course_code": "HH2090",
        "title": "SPECIAL TOPICS IN HISTORY I*~",
        "academic_units": "3.0 AU",
        "school_category": "Minor in History",
        "exam": null,
        "indexes": [
            {
                "index_number": "17618",
                "lessons": [
                    {
                        "type": "SEM",
                        "group": "SEM1",
                        "day": "THU",
                        "time": "1030-1320",
                        "venue": "LHS-TR+29",
                        "remark": ""
                    }
                ]
            }
        ]
    },
    {
        "course_code": "HH2125",
        "title": "THE WORLD IN 12 OBJECTS*~",
        "academic_units": "3.0 AU",
        "school_category": "Minor in History",
        "exam": null,
        "indexes": [
            {
                "index_number": "17619",
                "lessons": [
                    {
                        "type": "SEM",
                        "group": "SEM1",
                        "day": "MON",
                        "time": "0930-1220",
                        "venue": "LHS-TR+47",
                        "remark": ""
                    }
                ]
            }
        ]
    },
    {
        "course_code": "HH3001",
        "title": "HISTORIOGRAPHY: THEORY & METHODS*~",
        "academic_units": "3.0 AU",
        "school_category": "Minor in History",
        "exam": {
            "date": "24 November 2026",
            "day": "Tuesday",
            "time": "1.00 pm",
            "duration": "2 hr 30 min"
        },
        "indexes": [
            {
                "index_number": "17620",
                "lessons": [
                    {
                        "type": "SEM",
                        "group": "SEM1",
                        "day": "THU",
                        "time": "1130-1420",
                        "venue": "TR+66",
                        "remark": ""
                    }
                ]
            }
        ]
    },
    {
        "course_code": "HH3005",
        "title": "SEISMIC JAPAN: HISTORY, CULTURE & SOCIETY*~",
        "academic_units": "3.0 AU",
        "school_category": "Minor in History",
        "exam": null,
        "indexes": [
            {
                "index_number": "17625",
                "lessons": [
                    {
                        "type": "LEC/STUDIO",
                        "group": "LEC1",
                        "day": "FRI",
                        "time": "1030-1220",
                        "venue": "HSSAUDIT",
                        "remark": "Teaching Wk1-11,13"
                    },
                    {
                        "type": "LEC/STUDIO",
                        "group": "LEC1",
                        "day": "FRI",
                        "time": "1030-1220",
                        "venue": "LT24",
                        "remark": "Teaching Wk12"
                    },
                    {
                        "type": "TUT",
                        "group": "T1",
                        "day": "FRI",
                        "time": "1230-1320",
                        "venue": "TR+66",
                        "remark": "Teaching Wk2-13"
                    }
                ]
            },
            {
                "index_number": "17626",
                "lessons": [
                    {
                        "type": "LEC/STUDIO",
                        "group": "LEC1",
                        "day": "FRI",
                        "time": "1030-1220",
                        "venue": "HSSAUDIT",
                        "remark": "Teaching Wk1-11,13"
                    },
                    {
                        "type": "LEC/STUDIO",
                        "group": "LEC1",
                        "day": "FRI",
                        "time": "1030-1220",
                        "venue": "LT24",
                        "remark": "Teaching Wk12"
                    },
                    {
                        "type": "TUT",
                        "group": "T2",
                        "day": "FRI",
                        "time": "1330-1420",
                        "venue": "TR+66",
                        "remark": "Teaching Wk2-13"
                    }
                ]
            },
            {
                "index_number": "17627",
                "lessons": [
                    {
                        "type": "LEC/STUDIO",
                        "group": "LEC1",
                        "day": "FRI",
                        "time": "1030-1220",
                        "venue": "HSSAUDIT",
                        "remark": "Teaching Wk1-11,13"
                    },
                    {
                        "type": "LEC/STUDIO",
                        "group": "LEC1",
                        "day": "FRI",
                        "time": "1030-1220",
                        "venue": "LT24",
                        "remark": "Teaching Wk12"
                    },
                    {
                        "type": "TUT",
                        "group": "T3",
                        "day": "FRI",
                        "time": "1430-1520",
                        "venue": "TR+66",
                        "remark": "Teaching Wk2-13"
                    }
                ]
            },
            {
                "index_number": "17628",
                "lessons": [
                    {
                        "type": "LEC/STUDIO",
                        "group": "LEC1",
                        "day": "FRI",
                        "time": "1030-1220",
                        "venue": "HSSAUDIT",
                        "remark": "Teaching Wk1-11,13"
                    },
                    {
                        "type": "LEC/STUDIO",
                        "group": "LEC1",
                        "day": "FRI",
                        "time": "1030-1220",
                        "venue": "LT24",
                        "remark": "Teaching Wk12"
                    },
                    {
                        "type": "TUT",
                        "group": "T4",
                        "day": "FRI",
                        "time": "1530-1620",
                        "venue": "TR+66",
                        "remark": "Teaching Wk2-13"
                    }
                ]
            }
        ]
    },
    {
        "course_code": "HH3007",
        "title": "SOUTHEAST ASIAN-CHINA INTERACTIONS*~",
        "academic_units": "3.0 AU",
        "school_category": "Minor in History",
        "exam": null,
        "indexes": [
            {
                "index_number": "17621",
                "lessons": [
                    {
                        "type": "SEM",
                        "group": "SEM1",
                        "day": "TUE",
                        "time": "1430-1720",
                        "venue": "TR+109",
                        "remark": ""
                    }
                ]
            }
        ]
    },
    {
        "course_code": "HH3017",
        "title": "WORLD ENVIRONMENTAL HISTORY*~",
        "academic_units": "3.0 AU",
        "school_category": "Minor in History",
        "exam": null,
        "indexes": [
            {
                "index_number": "17637",
                "lessons": [
                    {
                        "type": "SEM",
                        "group": "SEM1",
                        "day": "THU",
                        "time": "0930-1220",
                        "venue": "LHS-TR+44",
                        "remark": ""
                    }
                ]
            }
        ]
    },
    {
        "course_code": "HH3019",
        "title": "HISTORY OF THE BODY*~",
        "academic_units": "3.0 AU",
        "school_category": "Minor in History",
        "exam": {
            "date": "25 November 2026",
            "day": "Wednesday",
            "time": "1.00 pm",
            "duration": "2 hr 30 min"
        },
        "indexes": [
            {
                "index_number": "17623",
                "lessons": [
                    {
                        "type": "SEM",
                        "group": "SEM1",
                        "day": "WED",
                        "time": "1430-1720",
                        "venue": "LHS-TR+31",
                        "remark": ""
                    }
                ]
            }
        ]
    },
    {
        "course_code": "HH3090",
        "title": "SPECIAL TOPICS IN HISTORY II*~",
        "academic_units": "3.0 AU",
        "school_category": "Minor in History",
        "exam": null,
        "indexes": [
            {
                "index_number": "17629",
                "lessons": [
                    {
                        "type": "SEM",
                        "group": "SEM1",
                        "day": "WED",
                        "time": "1030-1320",
                        "venue": "HSSSEMRM7",
                        "remark": ""
                    }
                ]
            }
        ]
    },
    {
        "course_code": "HH4003",
        "title": "THE SILK ROAD: OLD & NEW*~",
        "academic_units": "4.0 AU",
        "school_category": "Minor in History",
        "exam": null,
        "indexes": [
            {
                "index_number": "17630",
                "lessons": [
                    {
                        "type": "SEM",
                        "group": "SEM1",
                        "day": "WED",
                        "time": "1430-1820",
                        "venue": "TR+92",
                        "remark": ""
                    }
                ]
            }
        ]
    },
    {
        "course_code": "HH4010",
        "title": "ANTICOLONIAL RESISTANCE IN THE BRITISH EMPIRE*~",
        "academic_units": "4.0 AU",
        "school_category": "Minor in History",
        "exam": null,
        "indexes": [
            {
                "index_number": "17631",
                "lessons": [
                    {
                        "type": "SEM",
                        "group": "SEM1",
                        "day": "TUE",
                        "time": "1030-1420",
                        "venue": "TR+114",
                        "remark": ""
                    }
                ]
            }
        ]
    },
    {
        "course_code": "HH4020",
        "title": "SCIENCE, TECHNOLOGY, & SCIENCE FICTION*~",
        "academic_units": "4.0 AU",
        "school_category": "Minor in History",
        "exam": null,
        "indexes": [
            {
                "index_number": "17633",
                "lessons": [
                    {
                        "type": "SEM",
                        "group": "SEM1",
                        "day": "MON",
                        "time": "0930-1320",
                        "venue": "HSSSEMRM7",
                        "remark": ""
                    }
                ]
            }
        ]
    },
    {
        "course_code": "HH4029",
        "title": "HISTORY OF MODERN CHINA & COLONIAL HONG KONG, C.1945-1997*~",
        "academic_units": "4.0 AU",
        "school_category": "Minor in History",
        "exam": null,
        "indexes": [
            {
                "index_number": "17634",
                "lessons": [
                    {
                        "type": "SEM",
                        "group": "SEM1",
                        "day": "MON",
                        "time": "1330-1720",
                        "venue": "LHS-TR+54",
                        "remark": ""
                    }
                ]
            }
        ]
    },
    {
        "course_code": "HH4046",
        "title": "THE URBAN COAST*~",
        "academic_units": "4.0 AU",
        "school_category": "Minor in History",
        "exam": null,
        "indexes": [
            {
                "index_number": "17635",
                "lessons": [
                    {
                        "type": "SEM",
                        "group": "SEM1",
                        "day": "FRI",
                        "time": "1530-1920",
                        "venue": "LHS-TR+36",
                        "remark": ""
                    }
                ]
            }
        ]
    },
    {
        "course_code": "HH4092",
        "title": "SPECIAL TOPICS IN HISTORY- WORLD HISTORY*~",
        "academic_units": "4.0 AU",
        "school_category": "Minor in History",
        "exam": null,
        "indexes": [
            {
                "index_number": "17636",
                "lessons": [
                    {
                        "type": "SEM",
                        "group": "SEM1",
                        "day": "WED",
                        "time": "1030-1420",
                        "venue": "LHS-TR+41",
                        "remark": ""
                    }
                ]
            }
        ]
    }
]